finparse/__init__.py
finparse-0.2.0.dist-info/LICENSE
finparse-0.2.0.dist-info/WHEEL
finparse-0.2.0.dist-info/METADATA
finparse-0.2.0.dist-info/RECORD
